dw/__init__.py
py_dw-1.0.0.data/scripts/dw
py_dw-1.0.0.dist-info/LICENSE
py_dw-1.0.0.dist-info/METADATA
py_dw-1.0.0.dist-info/WHEEL
py_dw-1.0.0.dist-info/top_level.txt
py_dw-1.0.0.dist-info/RECORD
