Metadata-Version: 2.1
Name: py-dw
Version: 1.0.0
Summary: Data Wrangler (dw)
Home-page: https://github.com/MountainField/dw
Author: Takahide Nogayama
Author-email: nogayama@gmail.com
License: IBM
Download-URL: https://github.com/MountainField/dw/releases
Platform: UNKNOWN
License-File: LICENSE
